cool_mapMapboxRoute/__init__.py
cool_mapMapboxRoute/route_mapbox.py
cool_mapMapboxRoute-0.0.3.dist-info/LICENSE.txt
cool_mapMapboxRoute-0.0.3.dist-info/METADATA
cool_mapMapboxRoute-0.0.3.dist-info/WHEEL
cool_mapMapboxRoute-0.0.3.dist-info/top_level.txt
cool_mapMapboxRoute-0.0.3.dist-info/RECORD
