Metadata-Version: 2.1
Name: cool-mapMapboxRoute
Version: 0.0.3
Summary: For generating route path and estimated time
Home-page: https://github.com/swarupOGM/mapbox_route_estimation
Author: Swarup Adhikary
Author-email: swarupovo@gmail.com
Classifier: Programming Language :: Python :: 3
Classifier: License :: OSI Approved :: MIT License
Classifier: Operating System :: OS Independent
Requires-Python: >=3.5
License-File: LICENSE.txt
